{"cameraMode":{"drawMode":0,"name":"Shaded","section":"Shading Mode"},"sceneLighting":true,"audioPlay":false,"sceneViewState":{"m_AlwaysRefresh":false,"showFog":true,"showSkybox":true,"showFlares":true,"showImageEffects":true,"showParticleSystems":true,"showVisualEffectGraphs":true,"m_FxEnabled":true},"in2DMode":false,"pivot":{"x":0.0,"y":2.0,"z":-13.5},"rotation":{"x":-0.29294902086257937,"y":-0.6927456259727478,"z":0.3740321397781372,"w":-0.5428347587585449},"size":10.879558563232422,"orthographic":false}